setup.py
vebootstrap/__init__.py
vebootstrap/__main__.py
vebootstrap/config.py
vebootstrap/context.py
vebootstrap/create_bootstrap.py
vebootstrap/init.py
vebootstrap/pywinpackage.py
vebootstrap.egg-info/PKG-INFO
vebootstrap.egg-info/SOURCES.txt
vebootstrap.egg-info/dependency_links.txt
vebootstrap.egg-info/not-zip-safe
vebootstrap.egg-info/requires.txt
vebootstrap.egg-info/top_level.txt