Metadata-Version: 1.1
Name: vebootstrap
Version: 0.0.13
Summary: Virtualenv bootstrapper
Home-page: https://github.com/tomoemon/vebootstrap
Author: tomoemon
Author-email: bach48+github_tomoemon@gmail.com
License: MIT
Platform: POSIX
Platform: Windows
Platform: Mac OS X
Classifier: Development Status :: 4 - Beta
Classifier: Intended Audience :: Developers
Classifier: Operating System :: POSIX
Classifier: Operating System :: Microsoft :: Windows
Classifier: Programming Language :: Python :: 2.7
Classifier: Programming Language :: Python :: 3
Classifier: License :: OSI Approved :: MIT License
Classifier: Topic :: Utilities
Classifier: Topic :: Software Development
